Workbook

Sheet Hoja1
F1: Empresa Facturadora | G1: Código Cliente | H1: Cód. Concepto Facturable | I1: Fecha | J1: Descripción | K1: Tipo de IVA | L1: Unidades | M1: Importe Gastos | N1: Código Expediente | O1: Descripción Ampliada
A2: Expediente | B2: Cliente | C2: Emisor | D2: F. Lectura | E2: Asunto | F2: A | G2: B | H2: C | I2: D | J2: E | K2: F | L2: G | M2: H | N2: I | O2: J
A3: 00147 | B3: GREGORIO ANTONIO MESA DIAZ | C3: Agencia Estatal de Administración Tributaria | D3: 46154.597 | E3: Certificado estar al corriente | F3: 14 | G3: 0147 | H3: 3010 | I3: 46154.597 | J3: Aviso Notificacion | K3: 3 | L3: 1 | M3: =13*L3 -> 13 | N3: =IFERROR(VLOOKUP(TEXT(VALUE(TRIM(G3)),"00000"),EXP!$A:$B,2,FALSE),IFERROR(VLOOKUP(VALUE(TRIM(G3)),EXP!$A:$B,2,FALSE),"")) -> 00147-00398717 | O3: =CONCATENATE(J3,", ",E3,", ",C3) -> Aviso Notificacion, Certificado estar al corriente, Agencia Estatal de Administración Tributaria
A4: 0147 | B4: GREGORIO ANTONIO MESA DIAZ | C4: Agencia Estatal de Administración Tributaria | D4: 46153.634 | E4: Certificado de estar al corriente Positivo | F4: 14 | G4: 0147 | H4: 3010 | I4: 46153.634 | J4: Aviso Notificacion | K4: 3 | L4: 1 | M4: =13*L4 -> 13 | N4: =IFERROR(VLOOKUP(TEXT(VALUE(TRIM(G4)),"00000"),EXP!$A:$B,2,FALSE),IFERROR(VLOOKUP(VALUE(TRIM(G4)),EXP!$A:$B,2,FALSE),"")) -> 00147-00398717 | O4: =CONCATENATE(J4,", ",E4,", ",C4) -> Aviso Notificacion, Certificado de estar al corriente Positivo, Agencia Estatal de Administración Tributaria | P4: =IFERROR(VLOOKUP(TEXT(VALUE(TRIM(G4)),"00000"),EXP!$A:$B,2,FALSE),"")
A5: 0444 | B5: CENTRO INFANTIL PIN Y PON, SL | C5: Agencia Estatal de Administración Tributaria | D5: 46153.615 | E5: Diligencia de embargo de créditos | F5: 14 | G5: 0444 | H5: 3010 | I5: 46153.615 | J5: Aviso Notificacion | K5: 3 | L5: 1 | M5: =13*L5 -> 13 | N5: =IFERROR(VLOOKUP(TEXT(VALUE(TRIM(G5)),"00000"),EXP!$A:$B,2,FALSE),IFERROR(VLOOKUP(VALUE(TRIM(G5)),EXP!$A:$B,2,FALSE),"")) -> 00444-00400217 | O5: =CONCATENATE(J5,", ",E5,", ",C5) -> Aviso Notificacion, Diligencia de embargo de créditos, Agencia Estatal de Administración Tributaria | P5: =IFERROR(VLOOKUP(TEXT(VALUE(TRIM(G5)),"00000"),EXP!$A:$B,2,FALSE),"")
A6: 0546 | B6: FREMITEN,SL | C6: Agencia Estatal de Administración Tributaria | D6: 46133.349 | E6: Rehabilitacion NIF | F6: 14 | G6: 0546 | H6: 3010 | I6: 46133.349 | J6: Aviso Notificacion | K6: 3 | L6: 1 | M6: =13*L6 -> 13 | N6: =IFERROR(VLOOKUP(TEXT(VALUE(TRIM(G6)),"00000"),EXP!$A:$B,2,FALSE),IFERROR(VLOOKUP(VALUE(TRIM(G6)),EXP!$A:$B,2,FALSE),"")) -> 00546-00520424 | O6: =CONCATENATE(J6,", ",E6,", ",C6) -> Aviso Notificacion, Rehabilitacion NIF, Agencia Estatal de Administración Tributaria | P6: =IFERROR(VLOOKUP(TEXT(VALUE(TRIM(G6)),"00000"),EXP!$A:$B,2,FALSE),"")
A7: 0966 | B7: SANTIAGO MELIAN SUAREZ | C7: Agencia Estatal de Administración Tributaria | D7: 46153.607 | E7: Diligencia de embargo de créditos | F7: 14 | G7: 0966 | H7: 3010 | I7: 46153.607 | J7: Aviso Notificacion | K7: 3 | L7: 1 | M7: =13*L7 -> 13 | N7: =IFERROR(VLOOKUP(TEXT(VALUE(TRIM(G7)),"00000"),EXP!$A:$B,2,FALSE),IFERROR(VLOOKUP(VALUE(TRIM(G7)),EXP!$A:$B,2,FALSE),"")) | O7: =CONCATENATE(J7,", ",E7,", ",C7) -> Aviso Notificacion, Diligencia de embargo de créditos, Agencia Estatal de Administración Tributaria | P7: =IFERROR(VLOOKUP(TEXT(VALUE(TRIM(G7)),"00000"),EXP!$A:$B,2,FALSE),"")
A8: 1104 | B8: TODOCEMENTO, SLU | C8: Agencia Estatal de Administración Tributaria | D8: 46154.601 | E8: Providencia de apremio | F8: 14 | G8: 1104 | H8: 3010 | I8: 46154.601 | J8: Aviso Notificacion | K8: 3 | L8: 1 | M8: =13*L8 -> 13 | N8: =IFERROR(VLOOKUP(TEXT(VALUE(TRIM(G8)),"00000"),EXP!$A:$B,2,FALSE),IFERROR(VLOOKUP(VALUE(TRIM(G8)),EXP!$A:$B,2,FALSE),"")) -> 01104-00404417 | O8: =CONCATENATE(J8,", ",E8,", ",C8) -> Aviso Notificacion, Providencia de apremio, Agencia Estatal de Administración Tributaria | P8: =IFERROR(VLOOKUP(TEXT(VALUE(TRIM(G8)),"00000"),EXP!$A:$B,2,FALSE),"")
A9: 1245 | B9: REPAMAGRI SL | C9: Agencia Estatal de Administración Tributaria | D9: 46147.611 | E9: Levantamiento de embargo de créditos | F9: 14 | G9: 1245 | H9: 3010 | I9: 46147.611 | J9: Aviso Notificacion | K9: 3 | L9: 1 | M9: =13*L9 -> 13 | N9: =IFERROR(VLOOKUP(TEXT(VALUE(TRIM(G9)),"00000"),EXP!$A:$B,2,FALSE),IFERROR(VLOOKUP(VALUE(TRIM(G9)),EXP!$A:$B,2,FALSE),"")) -> 01245-00405717 | O9: =CONCATENATE(J9,", ",E9,", ",C9) -> Aviso Notificacion, Levantamiento de embargo de créditos, Agencia Estatal de Administración Tributaria | P9: =IFERROR(VLOOKUP(TEXT(VALUE(TRIM(G9)),"00000"),EXP!$A:$B,2,FALSE),"")
A10: 1815 | B10: CRISTALERIA CRISTALFUERT, SL | C10: Agencia Estatal de Administración Tributaria | D10: 46156.423 | E10: Reiteramiento de una diligencia de embargo de creditos | F10: 14 | G10: 1815 | H10: 3010 | I10: 46156.423 | J10: Aviso Notificacion | K10: 3 | L10: 1 | M10: =13*L10 -> 13 | N10: =IFERROR(VLOOKUP(TEXT(VALUE(TRIM(G10)),"00000"),EXP!$A:$B,2,FALSE),IFERROR(VLOOKUP(VALUE(TRIM(G10)),EXP!$A:$B,2,FALSE),"")) -> 01815-00416517 | O10: =CONCATENATE(J10,", ",E10,", ",C10) -> Aviso Notificacion, Reiteramiento de una diligencia de embargo de creditos, Agencia Estatal de Administración Tributaria | P10: =IFERROR(VLOOKUP(TEXT(VALUE(TRIM(G10)),"00000"),EXP!$A:$B,2,FALSE),"")
A11: 1960 | B11: BEATRIZ GUTIERREZ FLORES | C11: Agencia Estatal de Administración Tributaria | D11: 46154.618 | E11: Providencia de apremio | F11: 14 | G11: 1960 | H11: 3010 | I11: 46154.618 | J11: Aviso Notificacion | K11: 3 | L11: 1 | M11: =13*L11 -> 13 | N11: =IFERROR(VLOOKUP(TEXT(VALUE(TRIM(G11)),"00000"),EXP!$A:$B,2,FALSE),IFERROR(VLOOKUP(VALUE(TRIM(G11)),EXP!$A:$B,2,FALSE),"")) -> 01960-00423717 | O11: =CONCATENATE(J11,", ",E11,", ",C11) -> Aviso Notificacion, Providencia de apremio, Agencia Estatal de Administración Tributaria | P11: =IFERROR(VLOOKUP(TEXT(VALUE(TRIM(G11)),"00000"),EXP!$A:$B,2,FALSE),"")
A12: 1985 | B12: CHEN SI | C12: Agencia Estatal de Administración Tributaria | D12: 46133.359 | E12: Procedimiento sancionador Renta 2022 | F12: 14 | G12: 1985 | H12: 3010 | I12: 46133.359 | J12: Aviso Notificacion | K12: 3 | L12: 1 | M12: =13*L12 -> 13 | N12: =IFERROR(VLOOKUP(TEXT(VALUE(TRIM(G12)),"00000"),EXP!$A:$B,2,FALSE),IFERROR(VLOOKUP(VALUE(TRIM(G12)),EXP!$A:$B,2,FALSE),"")) -> 01985-00425817 | O12: =CONCATENATE(J12,", ",E12,", ",C12) -> Aviso Notificacion, Procedimiento sancionador Renta 2022, Agencia Estatal de Administración Tributaria | P12: =IFERROR(VLOOKUP(TEXT(VALUE(TRIM(G12)),"00000"),EXP!$A:$B,2,FALSE),"")
A13: 2149 | B13: HUI CHEN | C13: Agencia Estatal de Administración Tributaria | D13: 46139.531 | E13: Embargo de bienes muebles | F13: 14 | G13: 2149 | H13: 3010 | I13: 46139.531 | J13: Aviso Notificacion | K13: 3 | L13: 1 | M13: =13*L13 -> 13 | N13: =IFERROR(VLOOKUP(TEXT(VALUE(TRIM(G13)),"00000"),EXP!$A:$B,2,FALSE),IFERROR(VLOOKUP(VALUE(TRIM(G13)),EXP!$A:$B,2,FALSE),"")) -> 02149-00537226 | O13: =CONCATENATE(J13,", ",E13,", ",C13) -> Aviso Notificacion, Embargo de bienes muebles, Agencia Estatal de Administración Tributaria | P13: =IFERROR(VLOOKUP(TEXT(VALUE(TRIM(G13)),"00000"),EXP!$A:$B,2,FALSE),"")
A14: 2248 | B14: JOVANNA DEL CARMEN LARSSON UMPIERREZ | C14: Agencia Estatal de Administración Tributaria | D14: 46161.618 | E14: Compensacion de deuda | F14: 14 | G14: 2248 | H14: 3010 | I14: 46161.618 | J14: Aviso Notificacion | K14: 3 | L14: 1 | M14: =13*L14 -> 13 | N14: =IFERROR(VLOOKUP(TEXT(VALUE(TRIM(G14)),"00000"),EXP!$A:$B,2,FALSE),IFERROR(VLOOKUP(VALUE(TRIM(G14)),EXP!$A:$B,2,FALSE),"")) -> 02248-00492220 | O14: =CONCATENATE(J14,", ",E14,", ",C14) -> Aviso Notificacion, Compensacion de deuda, Agencia Estatal de Administración Tributaria | P14: =IFERROR(VLOOKUP(TEXT(VALUE(TRIM(G14)),"00000"),EXP!$A:$B,2,FALSE),"")
A15: 2248 | B15: PALOMA LIDIA RODRIGUEZ ALONSO | C15: Agencia Estatal de Administración Tributaria | D15: 46156.611 | E15: Comunicacion pago de devolucion | F15: 14 | G15: 2248 | H15: 3010 | I15: 46156.611 | J15: Aviso Notificacion | K15: 3 | L15: 1 | M15: =13*L15 -> 13 | N15: =IFERROR(VLOOKUP(TEXT(VALUE(TRIM(G15)),"00000"),EXP!$A:$B,2,FALSE),IFERROR(VLOOKUP(VALUE(TRIM(G15)),EXP!$A:$B,2,FALSE),"")) -> 02248-00492220 | O15: =CONCATENATE(J15,", ",E15,", ",C15) -> Aviso Notificacion, Comunicacion pago de devolucion, Agencia Estatal de Administración Tributaria | P15: =IFERROR(VLOOKUP(TEXT(VALUE(TRIM(G15)),"00000"),EXP!$A:$B,2,FALSE),"")
... A17: 2375 | B17: SARAY BIENVENIDA GAMEZ SANTOS | C17: Agencia Estatal de Administración Tributaria | D17: 46154.609 | E17: Providencia de apremio | F17: 14 | G17: 2375 | H17: 3010 | I17: 46154.609 | J17: Aviso Notificacion | K17: 3 | L17: 1 | M17: =13*L17 -> 13 | N17: =IFERROR(VLOOKUP(TEXT(VALUE(TRIM(G17)),"00000"),EXP!$A:$B,2,FALSE),IFERROR(VLOOKUP(VALUE(TRIM(G17)),EXP!$A:$B,2,FALSE),"")) -> 02375-00505722 | O17: =CONCATENATE(J17,", ",E17,", ",C17) -> Aviso Notificacion, Providencia de apremio, Agencia Estatal de Administración Tributaria | P17: =IFERROR(VLOOKUP(TEXT(VALUE(TRIM(G17)),"00000"),EXP!$A:$B,2,FALSE),"")
A18: 2375 | B18: SARAY BIENVENIDA GAMEZ SANTOS | C18: Agencia Estatal de Administración Tributaria | D18: 46154.612 | E18: Providencia de apremio | F18: 14 | G18: 2375 | H18: 3010 | I18: 46154.612 | J18: Aviso Notificacion | K18: 3 | L18: 1 | M18: =13*L18 -> 13 | N18: =IFERROR(VLOOKUP(TEXT(VALUE(TRIM(G18)),"00000"),EXP!$A:$B,2,FALSE),IFERROR(VLOOKUP(VALUE(TRIM(G18)),EXP!$A:$B,2,FALSE),"")) -> 02375-00505722 | O18: =CONCATENATE(J18,", ",E18,", ",C18) -> Aviso Notificacion, Providencia de apremio, Agencia Estatal de Administración Tributaria
A19: 2383 | B19: ORLEXNYS LOPEZ GONZALEZ | C19: Agencia Estatal de Administración Tributaria | D19: 46156.611 | E19: Comunicación pago de devolucion | F19: 14 | G19: 2383 | H19: 3010 | I19: 46156.611 | J19: Aviso Notificacion | K19: 3 | L19: 1 | M19: =13*L19 -> 13 | N19: =IFERROR(VLOOKUP(TEXT(VALUE(TRIM(G19)),"00000"),EXP!$A:$B,2,FALSE),IFERROR(VLOOKUP(VALUE(TRIM(G19)),EXP!$A:$B,2,FALSE),"")) -> 02383-00507222 | O19: =CONCATENATE(J19,", ",E19,", ",C19) -> Aviso Notificacion, Comunicación pago de devolucion, Agencia Estatal de Administración Tributaria
A20: 2383 | B20: ORLEXNYS LOPEZ GONZALEZ | C20: Agencia Estatal de Administración Tributaria | D20: 46161.399 | E20: Compensacion de deuda | F20: 14 | G20: 2383 | H20: 3010 | I20: 46161.399 | J20: Aviso Notificacion | K20: 3 | L20: 1 | M20: =13*L20 -> 13 | N20: =IFERROR(VLOOKUP(TEXT(VALUE(TRIM(G20)),"00000"),EXP!$A:$B,2,FALSE),IFERROR(VLOOKUP(VALUE(TRIM(G20)),EXP!$A:$B,2,FALSE),"")) -> 02383-00507222 | O20: =CONCATENATE(J20,", ",E20,", ",C20) -> Aviso Notificacion, Compensacion de deuda, Agencia Estatal de Administración Tributaria
A21: 2444 | B21: TERREHOSTE SL | C21: Agencia Estatal de Administración Tributaria | D21: 46161.394 | E21: Certificado de estar al corriente AEAT-Negativo | F21: 14 | G21: 2444 | H21: 3010 | I21: 46161.394 | J21: Aviso Notificacion | K21: 3 | L21: 1 | M21: =13*L21 -> 13 | N21: =IFERROR(VLOOKUP(TEXT(VALUE(TRIM(G21)),"00000"),EXP!$A:$B,2,FALSE),IFERROR(VLOOKUP(VALUE(TRIM(G21)),EXP!$A:$B,2,FALSE),"")) -> 02444-00519124 | O21: =CONCATENATE(J21,", ",E21,", ",C21) -> Aviso Notificacion, Certificado de estar al corriente AEAT-Negativo, Agencia Estatal de Administración Tributaria
A22: 2444 | B22: TERREHOSTE SL | C22: Agencia Estatal de Administración Tributaria | D22: 46133.438 | E22: Tramite de alegaciones | F22: 14 | G22: 2444 | H22: 3010 | I22: 46133.438 | J22: Aviso Notificacion | K22: 3 | L22: 1 | M22: =13*L22 -> 13 | N22: =IFERROR(VLOOKUP(TEXT(VALUE(TRIM(G22)),"00000"),EXP!$A:$B,2,FALSE),IFERROR(VLOOKUP(VALUE(TRIM(G22)),EXP!$A:$B,2,FALSE),"")) -> 02444-00519124 | O22: =CONCATENATE(J22,", ",E22,", ",C22) -> Aviso Notificacion, Tramite de alegaciones, Agencia Estatal de Administración Tributaria
A23: 2444 | B23: TERREHOSTE SL | C23: Agencia Estatal de Administración Tributaria | D23: 46161.396 | E23: IRPF 2025 | F23: 14 | G23: 2444 | H23: 3010 | I23: 46161.396 | J23: Aviso Notificacion | K23: 3 | L23: 1 | M23: =13*L23 -> 13 | N23: =IFERROR(VLOOKUP(TEXT(VALUE(TRIM(G23)),"00000"),EXP!$A:$B,2,FALSE),IFERROR(VLOOKUP(VALUE(TRIM(G23)),EXP!$A:$B,2,FALSE),"")) -> 02444-00519124 | O23: =CONCATENATE(J23,", ",E23,", ",C23) -> Aviso Notificacion, IRPF 2025, Agencia Estatal de Administración Tributaria
A24: 2557 | B24: MONTSERRAT AMAYA CARBALLO | C24: Agencia Estatal de Administración Tributaria | D24: 46139.533 | E24: Comunicacion familia numerosa | F24: 14 | G24: 2557 | H24: 3010 | I24: 46139.533 | J24: Aviso Notificacion | K24: 3 | L24: 1 | M24: =13*L24 -> 13 | N24: =IFERROR(VLOOKUP(TEXT(VALUE(TRIM(G24)),"00000"),EXP!$A:$B,2,FALSE),IFERROR(VLOOKUP(VALUE(TRIM(G24)),EXP!$A:$B,2,FALSE),"")) -> 02557-00532525 | O24: =CONCATENATE(J24,", ",E24,", ",C24) -> Aviso Notificacion, Comunicacion familia numerosa, Agencia Estatal de Administración Tributaria
A25: 2580 | B25: FRANCISCO JAVIER RODRIGUEZ GARCIA | C25: Agencia Estatal de Administración Tributaria | D25: 46149.607 | E25: Comunicación pago devolución | F25: 14 | G25: 2580 | H25: 3010 | I25: 46149.607 | J25: Aviso Notificacion | K25: 3 | L25: 1 | M25: =13*L25 -> 13 | N25: =IFERROR(VLOOKUP(TEXT(VALUE(TRIM(G25)),"00000"),EXP!$A:$B,2,FALSE),IFERROR(VLOOKUP(VALUE(TRIM(G25)),EXP!$A:$B,2,FALSE),"")) -> 02580-00535825 | O25: =CONCATENATE(J25,", ",E25,", ",C25) -> Aviso Notificacion, Comunicación pago devolución, Agencia Estatal de Administración Tributaria
A26: 2580 | B26: FRANCISCO JAVIER RODRIGUEZ GARCIA | C26: Agencia Estatal de Administración Tributaria | D26: 46153.623 | E26: Acuerdo de compensación de deuda | F26: 14 | G26: 2580 | H26: 3010 | I26: 46153.623 | J26: Aviso Notificacion | K26: 3 | L26: 1 | M26: =13*L26 -> 13 | N26: =IFERROR(VLOOKUP(TEXT(VALUE(TRIM(G26)),"00000"),EXP!$A:$B,2,FALSE),IFERROR(VLOOKUP(VALUE(TRIM(G26)),EXP!$A:$B,2,FALSE),"")) -> 02580-00535825 | O26: =CONCATENATE(J26,", ",E26,", ",C26) -> Aviso Notificacion, Acuerdo de compensación de deuda, Agencia Estatal de Administración Tributaria
A27: 2587 | B27: NICOLAS RODRIGUEZ CORONA | C27: Agencia Estatal de Administración Tributaria | D27: 46161.4 | E27: Diligencia de embargo de sueldo | F27: 14 | G27: 2587 | H27: 3010 | I27: 46161.4 | J27: Aviso Notificacion | K27: 3 | L27: 1 | M27: =13*L27 -> 13 | N27: =IFERROR(VLOOKUP(TEXT(VALUE(TRIM(G27)),"00000"),EXP!$A:$B,2,FALSE),IFERROR(VLOOKUP(VALUE(TRIM(G27)),EXP!$A:$B,2,FALSE),"")) -> 02587-00536626 | O27: =CONCATENATE(J27,", ",E27,", ",C27) -> Aviso Notificacion, Diligencia de embargo de sueldo, Agencia Estatal de Administración Tributaria
A28: 2587 | B28: NICOLAS RODRIGUEZ CORONA | C28: Agencia Estatal de Administración Tributaria | D28: 46161.401 | E28: Diligencia de embargo de sueldos | F28: 14 | G28: 2587 | H28: 3010 | I28: 46161.401 | J28: Aviso Notificacion | K28: 3 | L28: 1 | M28: =13*L28 -> 13 | N28: =IFERROR(VLOOKUP(TEXT(VALUE(TRIM(G28)),"00000"),EXP!$A:$B,2,FALSE),IFERROR(VLOOKUP(VALUE(TRIM(G28)),EXP!$A:$B,2,FALSE),"")) -> 02587-00536626 | O28: =CONCATENATE(J28,", ",E28,", ",C28) -> Aviso Notificacion, Diligencia de embargo de sueldos, Agencia Estatal de Administración Tributaria
A29: 2593 | B29: ALAIN MAHY HERNANDEZ VIZCAINO | C29: Agencia Estatal de Administración Tributaria | D29: 46161.397 | E29: Diligencia de embargo de sueldo | F29: 14 | G29: 2593 | H29: 3010 | I29: 46161.397 | J29: Aviso Notificacion | K29: 3 | L29: 1 | M29: =13*L29 -> 13 | N29: =IFERROR(VLOOKUP(TEXT(VALUE(TRIM(G29)),"00000"),EXP!$A:$B,2,FALSE),IFERROR(VLOOKUP(VALUE(TRIM(G29)),EXP!$A:$B,2,FALSE),"")) -> 02593-00538926 | O29: =CONCATENATE(J29,", ",E29,", ",C29) -> Aviso Notificacion, Diligencia de embargo de sueldo, Agencia Estatal de Administración Tributaria
... A127: 2519 | B127: FRANCISCO JAVIER MARTIN BACALLADO | C127: Tesoreria General de la Seguridad Social | D127: 46154.52 | E127: REGIMENES SEG. SOCIAL OBLIGADOS A RED / PROVIDENCIA DE APREMIO | F127: 14 | G127: 2519 | H127: 3010 | I127: 46154.52 | J127: Aviso Notificacion | K127: 3 | L127: 1 | M127: =13*L127 -> 13 | N127: =IFERROR(VLOOKUP(TEXT(VALUE(TRIM(G127)),"00000"),EXP!$A:$B,2,FALSE),IFERROR(VLOOKUP(VALUE(TRIM(G127)),EXP!$A:$B,2,FALSE),"")) -> 02519-00526924 | O127: =CONCATENATE(J127,", ",E127,", ",C127) -> Aviso Notificacion, REGIMENES SEG. SOCIAL OBLIGADOS A RED / PROVIDENCIA DE APREMIO, Tesoreria General de la Seguridad Social

Sheet EXP
A1: expte | B1: expte fact
A2: 5 | B2: 00005-00520324
A3: 8 | B3: 00008-00397817
A4: 22 | B4: 00022-00431617
A5: 28 | B5: 00028-00397917
A6: 43 | B6: 00043-00471118
A7: 45 | B7: 00045-00517823
A8: 59 | B8: 00059-00508422
A9: 61 | B9: 00061-00398017
A10: 68 | B10: 00068-00398117
A11: 70 | B11: 00070-00516023
A12: 99 | B12: 00099-00487320
A13: 104 | B13: 00104-00398217
... A854: 10600 | B854: 10600-00492620
